shipper/__init__.py
shipper/shipper.py
shipper-1.1.2.dist-info/METADATA
shipper-1.1.2.dist-info/WHEEL
shipper-1.1.2.dist-info/top_level.txt
shipper-1.1.2.dist-info/RECORD
