Metadata-Version: 2.1
Name: shipper
Version: 1.1.2
Summary: Package shipper
Home-page: UNKNOWN
Author: jaytrairat
Author-email: <jay.trairat@gmail.com>
License: UNKNOWN
Keywords: jaytrairat
Platform: UNKNOWN
Classifier: Programming Language :: Python :: 3
